modev/__init__.py
modev/build.py
modev/cli.py
modev/py.typed
python_modev-0.1.4.dist-info/METADATA
python_modev-0.1.4.dist-info/WHEEL
python_modev-0.1.4.dist-info/entry_points.txt
python_modev-0.1.4.dist-info/RECORD
