Metadata-Version: 2.4
Name: python-modev
Version: 0.1.4
Summary: Use Marimo notebooks as your development environment.
Author-email: ndendic <ndendic@gmail.com>
Requires-Python: >=3.12
Requires-Dist: marimo>=0.12.8
Requires-Dist: pyyaml>=6.0
Requires-Dist: typer>=0.15.2
